kitconcept/contactblock/__init__.py
kitconcept/contactblock/configure.zcml
kitconcept/contactblock/dependencies.zcml
kitconcept/contactblock/interfaces.py
kitconcept/contactblock/permissions.zcml
kitconcept/contactblock/profiles.zcml
kitconcept/contactblock/testing.py
kitconcept/contactblock/content/__init__.py
kitconcept/contactblock/controlpanels/__init__.py
kitconcept/contactblock/controlpanels/configure.zcml
kitconcept/contactblock/indexers/__init__.py
kitconcept/contactblock/indexers/configure.zcml
kitconcept/contactblock/locales/__init__.py
kitconcept/contactblock/locales/__main__.py
kitconcept/contactblock/locales/kitconcept.contactblock.pot
kitconcept/contactblock/locales/en/LC_MESSAGES/kitconcept.contactblock.mo
kitconcept/contactblock/locales/en/LC_MESSAGES/kitconcept.contactblock.po
kitconcept/contactblock/profiles/default/browserlayer.xml
kitconcept/contactblock/profiles/default/catalog.xml
kitconcept/contactblock/profiles/default/controlpanel.xml
kitconcept/contactblock/profiles/default/diff_tool.xml
kitconcept/contactblock/profiles/default/metadata.xml
kitconcept/contactblock/profiles/default/repositorytool.xml
kitconcept/contactblock/profiles/default/rolemap.xml
kitconcept/contactblock/profiles/default/types.xml
kitconcept/contactblock/profiles/default/registry/main.xml
kitconcept/contactblock/profiles/default/types/.gitkeep
kitconcept/contactblock/profiles/initial/metadata.xml
kitconcept/contactblock/profiles/uninstall/browserlayer.xml
kitconcept/contactblock/serializers/__init__.py
kitconcept/contactblock/serializers/configure.zcml
kitconcept/contactblock/serializers/contact.py
kitconcept/contactblock/serializers/summary.py
kitconcept/contactblock/services/configure.zcml
kitconcept/contactblock/services/contact_form.py
kitconcept/contactblock/services/form_ticket.py
kitconcept/contactblock/setuphandlers/__init__.py
kitconcept/contactblock/setuphandlers/initial.py
kitconcept/contactblock/setuphandlers/examplecontent/.gitkeep
kitconcept_contactblock-1.0.0a2.dist-info/METADATA
kitconcept_contactblock-1.0.0a2.dist-info/WHEEL
kitconcept_contactblock-1.0.0a2.dist-info/entry_points.txt
kitconcept_contactblock-1.0.0a2.dist-info/licenses/LICENSE.GPL
kitconcept_contactblock-1.0.0a2.dist-info/licenses/LICENSE.md
kitconcept_contactblock-1.0.0a2.dist-info/RECORD
