Metadata-Version: 2.4
Name: kitconcept.contactblock
Version: 1.0.0a2
Summary: Contact block by kitconcept
Project-URL: Homepage, https://github.com/kitconcept/volto-contact-block
Project-URL: PyPI, https://pypi.org/project/kitconcept.contactblock
Project-URL: Source, https://github.com/kitconcept/volto-contact-block
Project-URL: Tracker, https://github.com/kitconcept/volto-contact-block/issues
Author-email: "kitconcept, GmbH" <info@kitconcept.com>
License-Expression: GPL-2.0-only
License-File: LICENSE.GPL
License-File: LICENSE.md
Keywords: CMS,Plone,Python
Classifier: Development Status :: 3 - Alpha
Classifier: Environment :: Web Environment
Classifier: Framework :: Plone
Classifier: Framework :: Plone :: 6.1
Classifier: Framework :: Plone :: 6.2
Classifier: Framework :: Plone :: Addon
Classifier: Operating System :: OS Independent
Classifier: Programming Language :: Python
Classifier: Programming Language :: Python :: 3.11
Classifier: Programming Language :: Python :: 3.12
Classifier: Programming Language :: Python :: 3.13
Requires-Python: >=3.11
Requires-Dist: collective-person==1.0.0b3
Requires-Dist: plone-api
Requires-Dist: plone-restapi
Requires-Dist: plone-volto
Requires-Dist: products-cmfplone
Provides-Extra: test
Requires-Dist: horse-with-no-namespace; extra == 'test'
Requires-Dist: plone-app-testing; extra == 'test'
Requires-Dist: plone-restapi[test]; extra == 'test'
Requires-Dist: products-printingmailhost; extra == 'test'
Requires-Dist: pytest; extra == 'test'
Requires-Dist: pytest-cov; extra == 'test'
Requires-Dist: pytest-plone>=1.0.0a2; extra == 'test'
